mltune/__init__.py
mltune/base.py
mltune/lightgbm.py
mltune/plotting.py
mltune/sklearn.py
mltune/tuning.py
mltune/xgboost.py
mltune/wrappers/__init__.py
mltune-0.2.1.dist-info/licenses/LICENSE
sphinx/source/conf.py
tests/integration/test_autotune.py
tests/unit/test_tuning.py
tests/unit/test_wrappers.py
mltune-0.2.1.dist-info/METADATA
mltune-0.2.1.dist-info/WHEEL
mltune-0.2.1.dist-info/top_level.txt
mltune-0.2.1.dist-info/RECORD
