Metadata-Version: 2.4
Name: mltune
Version: 0.2.1
Summary: Lightweight toolkit for ML feature selection, calibration, voting optimization and reproducibility
Author-email: Volodymyr Gnateiko <birrgrrim@email.com>
License-Expression: MIT
Classifier: Programming Language :: Python :: 3
Classifier: Operating System :: OS Independent
Requires-Python: >=3.10
License-File: LICENSE
Requires-Dist: numpy
Requires-Dist: pandas
Requires-Dist: scikit-learn
Provides-Extra: dev
Requires-Dist: setuptools; extra == "dev"
Requires-Dist: pytest; extra == "dev"
Requires-Dist: pytest-cov; extra == "dev"
Requires-Dist: xgboost>=3.0; extra == "dev"
Requires-Dist: lightgbm>=4.0; extra == "dev"
Requires-Dist: matplotlib>=3.0; extra == "dev"
Requires-Dist: seaborn; extra == "dev"
Provides-Extra: xgboost
Requires-Dist: xgboost>=3.0; extra == "xgboost"
Provides-Extra: lgbm
Requires-Dist: lightgbm>=4.0; extra == "lgbm"
Provides-Extra: catboost
Requires-Dist: catboost; extra == "catboost"
Provides-Extra: viz
Requires-Dist: matplotlib>=3.0; extra == "viz"
Requires-Dist: seaborn; extra == "viz"
Provides-Extra: docs
Requires-Dist: sphinx; extra == "docs"
Requires-Dist: sphinx-rtd-theme; extra == "docs"
Requires-Dist: sphinx-autodoc-typehints; extra == "docs"
Requires-Dist: myst-parser; extra == "docs"
Provides-Extra: build
Requires-Dist: build; extra == "build"
Requires-Dist: twine; extra == "build"
Dynamic: license-file
